{
  "generated_at": "2026-05-04T15:01:09.885260+00:00",
  "phase": "Phase 61 Header/Label Inference Diagnostic for Numeric Table Gaps",
  "source_phase60_report": "reports\\phase60_text_extraction_gap_diagnostic\\phase60_text_extraction_gap_diagnostic_report.json",
  "subset_seed": 20260503,
  "subset_size_requested": 40,
  "subset_size_actual": 38,
  "numeric_table_without_labels_population": 38,
  "boolean_distributions": {
    "likely_table_present": {
      "true": 38
    },
    "likely_header_missing": {
      "true": 38
    },
    "likely_header_fragmented": {
      "false": 38
    },
    "likely_non_english_labels": {
      "false": 38
    },
    "likely_cyrillic_or_mixed_script_labels": {
      "false": 38
    },
    "likely_units_without_analyte_names": {
      "false": 38
    },
    "likely_analyte_names_without_units": {
      "false": 38
    },
    "inferable_by_neighbor_lines": {
      "false": 38
    },
    "inferable_by_table_geometry": {
      "true": 38
    },
    "inferable_by_generic_lab_units": {
      "false": 38
    },
    "inferable_by_multilingual_label_map": {
      "false": 38
    },
    "repeated_numeric_column_pattern": {
      "false": 38
    }
  },
  "recommended_strategy_distribution": {
    "table_geometry_header_inference": 38
  },
  "confidence_band_distribution": {
    "high": 38
  },
  "dominant_recommended_strategy": "table_geometry_header_inference",
  "recommended_phase62_target": {
    "title": "phase62_table_geometry_header_inference_prototype",
    "production_extractor_should_change_yet": false,
    "reason": "Most files have aligned numeric columns without recognised headers. Phase 62 should evaluate a NARROW geometry diagnostic prototype only \u2014 no production extractor change.",
    "dominant_strategy": "table_geometry_header_inference"
  },
  "production_extractor_should_change_yet": false,
  "subset": [
    {
      "safe_file_id": "corpus_file_000133",
      "file_type": "pdf",
      "extension": ".pdf",
      "page_count_bucket": "4_10",
      "structure_error": null,
      "text_length_bucket": "5000_20000",
      "numeric_density_bucket": "very_high_gt_50pct",
      "table_like_line_count_bucket": "zero",
      "short_line_ratio_bucket": "very_high_gt_50pct",
      "unit_pattern_count_bucket": "zero",
      "reference_range_pattern_count_bucket": "very_low_1_2",
      "repeated_numeric_column_pattern": false,
      "likely_table_present": true,
      "likely_header_missing": true,
      "likely_header_fragmented": false,
      "likely_non_english_labels": false,
      "likely_cyrillic_or_mixed_script_labels": false,
      "likely_units_without_analyte_names": false,
      "likely_analyte_names_without_units": false,
      "inferable_by_neighbor_lines": false,
      "inferable_by_table_geometry": true,
      "inferable_by_generic_lab_units": false,
      "inferable_by_multilingual_label_map": false,
      "recommended_strategy": "table_geometry_header_inference",
      "confidence_band": "high"
    },
    {
      "safe_file_id": "corpus_file_000215",
      "file_type": "pdf",
      "extension": ".pdf",
      "page_count_bucket": "2_3",
      "structure_error": null,
      "text_length_bucket": "1000_5000",
      "numeric_density_bucket": "high_30_50pct",
      "table_like_line_count_bucket": "zero",
      "short_line_ratio_bucket": "very_high_gt_50pct",
      "unit_pattern_count_bucket": "zero",
      "reference_range_pattern_count_bucket": "medium_6_15",
      "repeated_numeric_column_pattern": false,
      "likely_table_present": true,
      "likely_header_missing": true,
      "likely_header_fragmented": false,
      "likely_non_english_labels": false,
      "likely_cyrillic_or_mixed_script_labels": false,
      "likely_units_without_analyte_names": false,
      "likely_analyte_names_without_units": false,
      "inferable_by_neighbor_lines": false,
      "inferable_by_table_geometry": true,
      "inferable_by_generic_lab_units": false,
      "inferable_by_multilingual_label_map": false,
      "recommended_strategy": "table_geometry_header_inference",
      "confidence_band": "high"
    },
    {
      "safe_file_id": "corpus_file_000221",
      "file_type": "pdf",
      "extension": ".pdf",
      "page_count_bucket": "2_3",
      "structure_error": null,
      "text_length_bucket": "1000_5000",
      "numeric_density_bucket": "high_30_50pct",
      "table_like_line_count_bucket": "zero",
      "short_line_ratio_bucket": "very_high_gt_50pct",
      "unit_pattern_count_bucket": "zero",
      "reference_range_pattern_count_bucket": "zero",
      "repeated_numeric_column_pattern": false,
      "likely_table_present": true,
      "likely_header_missing": true,
      "likely_header_fragmented": false,
      "likely_non_english_labels": false,
      "likely_cyrillic_or_mixed_script_labels": false,
      "likely_units_without_analyte_names": false,
      "likely_analyte_names_without_units": false,
      "inferable_by_neighbor_lines": false,
      "inferable_by_table_geometry": true,
      "inferable_by_generic_lab_units": false,
      "inferable_by_multilingual_label_map": false,
      "recommended_strategy": "table_geometry_header_inference",
      "confidence_band": "high"
    },
    {
      "safe_file_id": "corpus_file_000223",
      "file_type": "pdf",
      "extension": ".pdf",
      "page_count_bucket": "1",
      "structure_error": null,
      "text_length_bucket": "200_1000",
      "numeric_density_bucket": "high_30_50pct",
      "table_like_line_count_bucket": "zero",
      "short_line_ratio_bucket": "very_high_gt_50pct",
      "unit_pattern_count_bucket": "zero",
      "reference_range_pattern_count_bucket": "zero",
      "repeated_numeric_column_pattern": false,
      "likely_table_present": true,
      "likely_header_missing": true,
      "likely_header_fragmented": false,
      "likely_non_english_labels": false,
      "likely_cyrillic_or_mixed_script_labels": false,
      "likely_units_without_analyte_names": false,
      "likely_analyte_names_without_units": false,
      "inferable_by_neighbor_lines": false,
      "inferable_by_table_geometry": true,
      "inferable_by_generic_lab_units": false,
      "inferable_by_multilingual_label_map": false,
      "recommended_strategy": "table_geometry_header_inference",
      "confidence_band": "high"
    },
    {
      "safe_file_id": "corpus_file_000233",
      "file_type": "pdf",
      "extension": ".pdf",
      "page_count_bucket": "1",
      "structure_error": null,
      "text_length_bucket": "200_1000",
      "numeric_density_bucket": "very_high_gt_50pct",
      "table_like_line_count_bucket": "zero",
      "short_line_ratio_bucket": "very_high_gt_50pct",
      "unit_pattern_count_bucket": "zero",
      "reference_range_pattern_count_bucket": "zero",
      "repeated_numeric_column_pattern": false,
      "likely_table_present": true,
      "likely_header_missing": true,
      "likely_header_fragmented": false,
      "likely_non_english_labels": false,
      "likely_cyrillic_or_mixed_script_labels": false,
      "likely_units_without_analyte_names": false,
      "likely_analyte_names_without_units": false,
      "inferable_by_neighbor_lines": false,
      "inferable_by_table_geometry": true,
      "inferable_by_generic_lab_units": false,
      "inferable_by_multilingual_label_map": false,
      "recommended_strategy": "table_geometry_header_inference",
      "confidence_band": "high"
    },
    {
      "safe_file_id": "corpus_file_000247",
      "file_type": "pdf",
      "extension": ".pdf",
      "page_count_bucket": "1",
      "structure_error": null,
      "text_length_bucket": "200_1000",
      "numeric_density_bucket": "very_high_gt_50pct",
      "table_like_line_count_bucket": "zero",
      "short_line_ratio_bucket": "very_high_gt_50pct",
      "unit_pattern_count_bucket": "zero",
      "reference_range_pattern_count_bucket": "zero",
      "repeated_numeric_column_pattern": false,
      "likely_table_present": true,
      "likely_header_missing": true,
      "likely_header_fragmented": false,
      "likely_non_english_labels": false,
      "likely_cyrillic_or_mixed_script_labels": false,
      "likely_units_without_analyte_names": false,
      "likely_analyte_names_without_units": false,
      "inferable_by_neighbor_lines": false,
      "inferable_by_table_geometry": true,
      "inferable_by_generic_lab_units": false,
      "inferable_by_multilingual_label_map": false,
      "recommended_strategy": "table_geometry_header_inference",
      "confidence_band": "high"
    },
    {
      "safe_file_id": "corpus_file_000249",
      "file_type": "pdf",
      "extension": ".pdf",
      "page_count_bucket": "1",
      "structure_error": null,
      "text_length_bucket": "200_1000",
      "numeric_density_bucket": "very_high_gt_50pct",
      "table_like_line_count_bucket": "zero",
      "short_line_ratio_bucket": "very_high_gt_50pct",
      "unit_pattern_count_bucket": "zero",
      "reference_range_pattern_count_bucket": "zero",
      "repeated_numeric_column_pattern": false,
      "likely_table_present": true,
      "likely_header_missing": true,
      "likely_header_fragmented": false,
      "likely_non_english_labels": false,
      "likely_cyrillic_or_mixed_script_labels": false,
      "likely_units_without_analyte_names": false,
      "likely_analyte_names_without_units": false,
      "inferable_by_neighbor_lines": false,
      "inferable_by_table_geometry": true,
      "inferable_by_generic_lab_units": false,
      "inferable_by_multilingual_label_map": false,
      "recommended_strategy": "table_geometry_header_inference",
      "confidence_band": "high"
    },
    {
      "safe_file_id": "corpus_file_000253",
      "file_type": "pdf",
      "extension": ".pdf",
      "page_count_bucket": "1",
      "structure_error": null,
      "text_length_bucket": "200_1000",
      "numeric_density_bucket": "very_high_gt_50pct",
      "table_like_line_count_bucket": "zero",
      "short_line_ratio_bucket": "very_high_gt_50pct",
      "unit_pattern_count_bucket": "zero",
      "reference_range_pattern_count_bucket": "zero",
      "repeated_numeric_column_pattern": false,
      "likely_table_present": true,
      "likely_header_missing": true,
      "likely_header_fragmented": false,
      "likely_non_english_labels": false,
      "likely_cyrillic_or_mixed_script_labels": false,
      "likely_units_without_analyte_names": false,
      "likely_analyte_names_without_units": false,
      "inferable_by_neighbor_lines": false,
      "inferable_by_table_geometry": true,
      "inferable_by_generic_lab_units": false,
      "inferable_by_multilingual_label_map": false,
      "recommended_strategy": "table_geometry_header_inference",
      "confidence_band": "high"
    },
    {
      "safe_file_id": "corpus_file_000256",
      "file_type": "pdf",
      "extension": ".pdf",
      "page_count_bucket": "1",
      "structure_error": null,
      "text_length_bucket": "200_1000",
      "numeric_density_bucket": "very_high_gt_50pct",
      "table_like_line_count_bucket": "zero",
      "short_line_ratio_bucket": "very_high_gt_50pct",
      "unit_pattern_count_bucket": "zero",
      "reference_range_pattern_count_bucket": "zero",
      "repeated_numeric_column_pattern": false,
      "likely_table_present": true,
      "likely_header_missing": true,
      "likely_header_fragmented": false,
      "likely_non_english_labels": false,
      "likely_cyrillic_or_mixed_script_labels": false,
      "likely_units_without_analyte_names": false,
      "likely_analyte_names_without_units": false,
      "inferable_by_neighbor_lines": false,
      "inferable_by_table_geometry": true,
      "inferable_by_generic_lab_units": false,
      "inferable_by_multilingual_label_map": false,
      "recommended_strategy": "table_geometry_header_inference",
      "confidence_band": "high"
    },
    {
      "safe_file_id": "corpus_file_000260",
      "file_type": "pdf",
      "extension": ".pdf",
      "page_count_bucket": "1",
      "structure_error": null,
      "text_length_bucket": "200_1000",
      "numeric_density_bucket": "very_high_gt_50pct",
      "table_like_line_count_bucket": "zero",
      "short_line_ratio_bucket": "very_high_gt_50pct",
      "unit_pattern_count_bucket": "zero",
      "reference_range_pattern_count_bucket": "zero",
      "repeated_numeric_column_pattern": false,
      "likely_table_present": true,
      "likely_header_missing": true,
      "likely_header_fragmented": false,
      "likely_non_english_labels": false,
      "likely_cyrillic_or_mixed_script_labels": false,
      "likely_units_without_analyte_names": false,
      "likely_analyte_names_without_units": false,
      "inferable_by_neighbor_lines": false,
      "inferable_by_table_geometry": true,
      "inferable_by_generic_lab_units": false,
      "inferable_by_multilingual_label_map": false,
      "recommended_strategy": "table_geometry_header_inference",
      "confidence_band": "high"
    },
    {
      "safe_file_id": "corpus_file_000268",
      "file_type": "pdf",
      "extension": ".pdf",
      "page_count_bucket": "1",
      "structure_error": null,
      "text_length_bucket": "200_1000",
      "numeric_density_bucket": "very_high_gt_50pct",
      "table_like_line_count_bucket": "zero",
      "short_line_ratio_bucket": "very_high_gt_50pct",
      "unit_pattern_count_bucket": "zero",
      "reference_range_pattern_count_bucket": "zero",
      "repeated_numeric_column_pattern": false,
      "likely_table_present": true,
      "likely_header_missing": true,
      "likely_header_fragmented": false,
      "likely_non_english_labels": false,
      "likely_cyrillic_or_mixed_script_labels": false,
      "likely_units_without_analyte_names": false,
      "likely_analyte_names_without_units": false,
      "inferable_by_neighbor_lines": false,
      "inferable_by_table_geometry": true,
      "inferable_by_generic_lab_units": false,
      "inferable_by_multilingual_label_map": false,
      "recommended_strategy": "table_geometry_header_inference",
      "confidence_band": "high"
    },
    {
      "safe_file_id": "corpus_file_000269",
      "file_type": "pdf",
      "extension": ".pdf",
      "page_count_bucket": "1",
      "structure_error": null,
      "text_length_bucket": "200_1000",
      "numeric_density_bucket": "very_high_gt_50pct",
      "table_like_line_count_bucket": "zero",
      "short_line_ratio_bucket": "very_high_gt_50pct",
      "unit_pattern_count_bucket": "zero",
      "reference_range_pattern_count_bucket": "zero",
      "repeated_numeric_column_pattern": false,
      "likely_table_present": true,
      "likely_header_missing": true,
      "likely_header_fragmented": false,
      "likely_non_english_labels": false,
      "likely_cyrillic_or_mixed_script_labels": false,
      "likely_units_without_analyte_names": false,
      "likely_analyte_names_without_units": false,
      "inferable_by_neighbor_lines": false,
      "inferable_by_table_geometry": true,
      "inferable_by_generic_lab_units": false,
      "inferable_by_multilingual_label_map": false,
      "recommended_strategy": "table_geometry_header_inference",
      "confidence_band": "high"
    },
    {
      "safe_file_id": "corpus_file_000270",
      "file_type": "pdf",
      "extension": ".pdf",
      "page_count_bucket": "1",
      "structure_error": null,
      "text_length_bucket": "200_1000",
      "numeric_density_bucket": "very_high_gt_50pct",
      "table_like_line_count_bucket": "zero",
      "short_line_ratio_bucket": "very_high_gt_50pct",
      "unit_pattern_count_bucket": "zero",
      "reference_range_pattern_count_bucket": "zero",
      "repeated_numeric_column_pattern": false,
      "likely_table_present": true,
      "likely_header_missing": true,
      "likely_header_fragmented": false,
      "likely_non_english_labels": false,
      "likely_cyrillic_or_mixed_script_labels": false,
      "likely_units_without_analyte_names": false,
      "likely_analyte_names_without_units": false,
      "inferable_by_neighbor_lines": false,
      "inferable_by_table_geometry": true,
      "inferable_by_generic_lab_units": false,
      "inferable_by_multilingual_label_map": false,
      "recommended_strategy": "table_geometry_header_inference",
      "confidence_band": "high"
    },
    {
      "safe_file_id": "corpus_file_000282",
      "file_type": "pdf",
      "extension": ".pdf",
      "page_count_bucket": "1",
      "structure_error": null,
      "text_length_bucket": "200_1000",
      "numeric_density_bucket": "very_high_gt_50pct",
      "table_like_line_count_bucket": "zero",
      "short_line_ratio_bucket": "very_high_gt_50pct",
      "unit_pattern_count_bucket": "zero",
      "reference_range_pattern_count_bucket": "zero",
      "repeated_numeric_column_pattern": false,
      "likely_table_present": true,
      "likely_header_missing": true,
      "likely_header_fragmented": false,
      "likely_non_english_labels": false,
      "likely_cyrillic_or_mixed_script_labels": false,
      "likely_units_without_analyte_names": false,
      "likely_analyte_names_without_units": false,
      "inferable_by_neighbor_lines": false,
      "inferable_by_table_geometry": true,
      "inferable_by_generic_lab_units": false,
      "inferable_by_multilingual_label_map": false,
      "recommended_strategy": "table_geometry_header_inference",
      "confidence_band": "high"
    },
    {
      "safe_file_id": "corpus_file_000293",
      "file_type": "pdf",
      "extension": ".pdf",
      "page_count_bucket": "1",
      "structure_error": null,
      "text_length_bucket": "200_1000",
      "numeric_density_bucket": "very_high_gt_50pct",
      "table_like_line_count_bucket": "zero",
      "short_line_ratio_bucket": "very_high_gt_50pct",
      "unit_pattern_count_bucket": "zero",
      "reference_range_pattern_count_bucket": "zero",
      "repeated_numeric_column_pattern": false,
      "likely_table_present": true,
      "likely_header_missing": true,
      "likely_header_fragmented": false,
      "likely_non_english_labels": false,
      "likely_cyrillic_or_mixed_script_labels": false,
      "likely_units_without_analyte_names": false,
      "likely_analyte_names_without_units": false,
      "inferable_by_neighbor_lines": false,
      "inferable_by_table_geometry": true,
      "inferable_by_generic_lab_units": false,
      "inferable_by_multilingual_label_map": false,
      "recommended_strategy": "table_geometry_header_inference",
      "confidence_band": "high"
    },
    {
      "safe_file_id": "corpus_file_000334",
      "file_type": "pdf",
      "extension": ".pdf",
      "page_count_bucket": "1",
      "structure_error": null,
      "text_length_bucket": "200_1000",
      "numeric_density_bucket": "very_high_gt_50pct",
      "table_like_line_count_bucket": "zero",
      "short_line_ratio_bucket": "very_high_gt_50pct",
      "unit_pattern_count_bucket": "zero",
      "reference_range_pattern_count_bucket": "zero",
      "repeated_numeric_column_pattern": false,
      "likely_table_present": true,
      "likely_header_missing": true,
      "likely_header_fragmented": false,
      "likely_non_english_labels": false,
      "likely_cyrillic_or_mixed_script_labels": false,
      "likely_units_without_analyte_names": false,
      "likely_analyte_names_without_units": false,
      "inferable_by_neighbor_lines": false,
      "inferable_by_table_geometry": true,
      "inferable_by_generic_lab_units": false,
      "inferable_by_multilingual_label_map": false,
      "recommended_strategy": "table_geometry_header_inference",
      "confidence_band": "high"
    },
    {
      "safe_file_id": "corpus_file_000343",
      "file_type": "pdf",
      "extension": ".pdf",
      "page_count_bucket": "1",
      "structure_error": null,
      "text_length_bucket": "200_1000",
      "numeric_density_bucket": "very_high_gt_50pct",
      "table_like_line_count_bucket": "zero",
      "short_line_ratio_bucket": "very_high_gt_50pct",
      "unit_pattern_count_bucket": "zero",
      "reference_range_pattern_count_bucket": "zero",
      "repeated_numeric_column_pattern": false,
      "likely_table_present": true,
      "likely_header_missing": true,
      "likely_header_fragmented": false,
      "likely_non_english_labels": false,
      "likely_cyrillic_or_mixed_script_labels": false,
      "likely_units_without_analyte_names": false,
      "likely_analyte_names_without_units": false,
      "inferable_by_neighbor_lines": false,
      "inferable_by_table_geometry": true,
      "inferable_by_generic_lab_units": false,
      "inferable_by_multilingual_label_map": false,
      "recommended_strategy": "table_geometry_header_inference",
      "confidence_band": "high"
    },
    {
      "safe_file_id": "corpus_file_000346",
      "file_type": "pdf",
      "extension": ".pdf",
      "page_count_bucket": "1",
      "structure_error": null,
      "text_length_bucket": "200_1000",
      "numeric_density_bucket": "very_high_gt_50pct",
      "table_like_line_count_bucket": "zero",
      "short_line_ratio_bucket": "very_high_gt_50pct",
      "unit_pattern_count_bucket": "zero",
      "reference_range_pattern_count_bucket": "zero",
      "repeated_numeric_column_pattern": false,
      "likely_table_present": true,
      "likely_header_missing": true,
      "likely_header_fragmented": false,
      "likely_non_english_labels": false,
      "likely_cyrillic_or_mixed_script_labels": false,
      "likely_units_without_analyte_names": false,
      "likely_analyte_names_without_units": false,
      "inferable_by_neighbor_lines": false,
      "inferable_by_table_geometry": true,
      "inferable_by_generic_lab_units": false,
      "inferable_by_multilingual_label_map": false,
      "recommended_strategy": "table_geometry_header_inference",
      "confidence_band": "high"
    },
    {
      "safe_file_id": "corpus_file_000354",
      "file_type": "pdf",
      "extension": ".pdf",
      "page_count_bucket": "1",
      "structure_error": null,
      "text_length_bucket": "200_1000",
      "numeric_density_bucket": "very_high_gt_50pct",
      "table_like_line_count_bucket": "zero",
      "short_line_ratio_bucket": "very_high_gt_50pct",
      "unit_pattern_count_bucket": "zero",
      "reference_range_pattern_count_bucket": "zero",
      "repeated_numeric_column_pattern": false,
      "likely_table_present": true,
      "likely_header_missing": true,
      "likely_header_fragmented": false,
      "likely_non_english_labels": false,
      "likely_cyrillic_or_mixed_script_labels": false,
      "likely_units_without_analyte_names": false,
      "likely_analyte_names_without_units": false,
      "inferable_by_neighbor_lines": false,
      "inferable_by_table_geometry": true,
      "inferable_by_generic_lab_units": false,
      "inferable_by_multilingual_label_map": false,
      "recommended_strategy": "table_geometry_header_inference",
      "confidence_band": "high"
    },
    {
      "safe_file_id": "corpus_file_000359",
      "file_type": "pdf",
      "extension": ".pdf",
      "page_count_bucket": "1",
      "structure_error": null,
      "text_length_bucket": "200_1000",
      "numeric_density_bucket": "very_high_gt_50pct",
      "table_like_line_count_bucket": "zero",
      "short_line_ratio_bucket": "very_high_gt_50pct",
      "unit_pattern_count_bucket": "zero",
      "reference_range_pattern_count_bucket": "zero",
      "repeated_numeric_column_pattern": false,
      "likely_table_present": true,
      "likely_header_missing": true,
      "likely_header_fragmented": false,
      "likely_non_english_labels": false,
      "likely_cyrillic_or_mixed_script_labels": false,
      "likely_units_without_analyte_names": false,
      "likely_analyte_names_without_units": false,
      "inferable_by_neighbor_lines": false,
      "inferable_by_table_geometry": true,
      "inferable_by_generic_lab_units": false,
      "inferable_by_multilingual_label_map": false,
      "recommended_strategy": "table_geometry_header_inference",
      "confidence_band": "high"
    },
    {
      "safe_file_id": "corpus_file_000372",
      "file_type": "pdf",
      "extension": ".pdf",
      "page_count_bucket": "1",
      "structure_error": null,
      "text_length_bucket": "200_1000",
      "numeric_density_bucket": "very_high_gt_50pct",
      "table_like_line_count_bucket": "zero",
      "short_line_ratio_bucket": "very_high_gt_50pct",
      "unit_pattern_count_bucket": "zero",
      "reference_range_pattern_count_bucket": "zero",
      "repeated_numeric_column_pattern": false,
      "likely_table_present": true,
      "likely_header_missing": true,
      "likely_header_fragmented": false,
      "likely_non_english_labels": false,
      "likely_cyrillic_or_mixed_script_labels": false,
      "likely_units_without_analyte_names": false,
      "likely_analyte_names_without_units": false,
      "inferable_by_neighbor_lines": false,
      "inferable_by_table_geometry": true,
      "inferable_by_generic_lab_units": false,
      "inferable_by_multilingual_label_map": false,
      "recommended_strategy": "table_geometry_header_inference",
      "confidence_band": "high"
    },
    {
      "safe_file_id": "corpus_file_000385",
      "file_type": "pdf",
      "extension": ".pdf",
      "page_count_bucket": "1",
      "structure_error": null,
      "text_length_bucket": "200_1000",
      "numeric_density_bucket": "high_30_50pct",
      "table_like_line_count_bucket": "zero",
      "short_line_ratio_bucket": "very_high_gt_50pct",
      "unit_pattern_count_bucket": "zero",
      "reference_range_pattern_count_bucket": "zero",
      "repeated_numeric_column_pattern": false,
      "likely_table_present": true,
      "likely_header_missing": true,
      "likely_header_fragmented": false,
      "likely_non_english_labels": false,
      "likely_cyrillic_or_mixed_script_labels": false,
      "likely_units_without_analyte_names": false,
      "likely_analyte_names_without_units": false,
      "inferable_by_neighbor_lines": false,
      "inferable_by_table_geometry": true,
      "inferable_by_generic_lab_units": false,
      "inferable_by_multilingual_label_map": false,
      "recommended_strategy": "table_geometry_header_inference",
      "confidence_band": "high"
    },
    {
      "safe_file_id": "corpus_file_000386",
      "file_type": "pdf",
      "extension": ".pdf",
      "page_count_bucket": "1",
      "structure_error": null,
      "text_length_bucket": "200_1000",
      "numeric_density_bucket": "high_30_50pct",
      "table_like_line_count_bucket": "zero",
      "short_line_ratio_bucket": "very_high_gt_50pct",
      "unit_pattern_count_bucket": "zero",
      "reference_range_pattern_count_bucket": "zero",
      "repeated_numeric_column_pattern": false,
      "likely_table_present": true,
      "likely_header_missing": true,
      "likely_header_fragmented": false,
      "likely_non_english_labels": false,
      "likely_cyrillic_or_mixed_script_labels": false,
      "likely_units_without_analyte_names": false,
      "likely_analyte_names_without_units": false,
      "inferable_by_neighbor_lines": false,
      "inferable_by_table_geometry": true,
      "inferable_by_generic_lab_units": false,
      "inferable_by_multilingual_label_map": false,
      "recommended_strategy": "table_geometry_header_inference",
      "confidence_band": "high"
    },
    {
      "safe_file_id": "corpus_file_000387",
      "file_type": "pdf",
      "extension": ".pdf",
      "page_count_bucket": "1",
      "structure_error": null,
      "text_length_bucket": "200_1000",
      "numeric_density_bucket": "high_30_50pct",
      "table_like_line_count_bucket": "zero",
      "short_line_ratio_bucket": "very_high_gt_50pct",
      "unit_pattern_count_bucket": "zero",
      "reference_range_pattern_count_bucket": "zero",
      "repeated_numeric_column_pattern": false,
      "likely_table_present": true,
      "likely_header_missing": true,
      "likely_header_fragmented": false,
      "likely_non_english_labels": false,
      "likely_cyrillic_or_mixed_script_labels": false,
      "likely_units_without_analyte_names": false,
      "likely_analyte_names_without_units": false,
      "inferable_by_neighbor_lines": false,
      "inferable_by_table_geometry": true,
      "inferable_by_generic_lab_units": false,
      "inferable_by_multilingual_label_map": false,
      "recommended_strategy": "table_geometry_header_inference",
      "confidence_band": "high"
    },
    {
      "safe_file_id": "corpus_file_000401",
      "file_type": "pdf",
      "extension": ".pdf",
      "page_count_bucket": "1",
      "structure_error": null,
      "text_length_bucket": "200_1000",
      "numeric_density_bucket": "high_30_50pct",
      "table_like_line_count_bucket": "zero",
      "short_line_ratio_bucket": "very_high_gt_50pct",
      "unit_pattern_count_bucket": "zero",
      "reference_range_pattern_count_bucket": "zero",
      "repeated_numeric_column_pattern": false,
      "likely_table_present": true,
      "likely_header_missing": true,
      "likely_header_fragmented": false,
      "likely_non_english_labels": false,
      "likely_cyrillic_or_mixed_script_labels": false,
      "likely_units_without_analyte_names": false,
      "likely_analyte_names_without_units": false,
      "inferable_by_neighbor_lines": false,
      "inferable_by_table_geometry": true,
      "inferable_by_generic_lab_units": false,
      "inferable_by_multilingual_label_map": false,
      "recommended_strategy": "table_geometry_header_inference",
      "confidence_band": "high"
    },
    {
      "safe_file_id": "corpus_file_000404",
      "file_type": "pdf",
      "extension": ".pdf",
      "page_count_bucket": "1",
      "structure_error": null,
      "text_length_bucket": "200_1000",
      "numeric_density_bucket": "high_30_50pct",
      "table_like_line_count_bucket": "zero",
      "short_line_ratio_bucket": "very_high_gt_50pct",
      "unit_pattern_count_bucket": "zero",
      "reference_range_pattern_count_bucket": "zero",
      "repeated_numeric_column_pattern": false,
      "likely_table_present": true,
      "likely_header_missing": true,
      "likely_header_fragmented": false,
      "likely_non_english_labels": false,
      "likely_cyrillic_or_mixed_script_labels": false,
      "likely_units_without_analyte_names": false,
      "likely_analyte_names_without_units": false,
      "inferable_by_neighbor_lines": false,
      "inferable_by_table_geometry": true,
      "inferable_by_generic_lab_units": false,
      "inferable_by_multilingual_label_map": false,
      "recommended_strategy": "table_geometry_header_inference",
      "confidence_band": "high"
    },
    {
      "safe_file_id": "corpus_file_000419",
      "file_type": "pdf",
      "extension": ".pdf",
      "page_count_bucket": "1",
      "structure_error": null,
      "text_length_bucket": "200_1000",
      "numeric_density_bucket": "high_30_50pct",
      "table_like_line_count_bucket": "zero",
      "short_line_ratio_bucket": "very_high_gt_50pct",
      "unit_pattern_count_bucket": "zero",
      "reference_range_pattern_count_bucket": "zero",
      "repeated_numeric_column_pattern": false,
      "likely_table_present": true,
      "likely_header_missing": true,
      "likely_header_fragmented": false,
      "likely_non_english_labels": false,
      "likely_cyrillic_or_mixed_script_labels": false,
      "likely_units_without_analyte_names": false,
      "likely_analyte_names_without_units": false,
      "inferable_by_neighbor_lines": false,
      "inferable_by_table_geometry": true,
      "inferable_by_generic_lab_units": false,
      "inferable_by_multilingual_label_map": false,
      "recommended_strategy": "table_geometry_header_inference",
      "confidence_band": "high"
    },
    {
      "safe_file_id": "corpus_file_000422",
      "file_type": "pdf",
      "extension": ".pdf",
      "page_count_bucket": "1",
      "structure_error": null,
      "text_length_bucket": "200_1000",
      "numeric_density_bucket": "high_30_50pct",
      "table_like_line_count_bucket": "zero",
      "short_line_ratio_bucket": "very_high_gt_50pct",
      "unit_pattern_count_bucket": "zero",
      "reference_range_pattern_count_bucket": "zero",
      "repeated_numeric_column_pattern": false,
      "likely_table_present": true,
      "likely_header_missing": true,
      "likely_header_fragmented": false,
      "likely_non_english_labels": false,
      "likely_cyrillic_or_mixed_script_labels": false,
      "likely_units_without_analyte_names": false,
      "likely_analyte_names_without_units": false,
      "inferable_by_neighbor_lines": false,
      "inferable_by_table_geometry": true,
      "inferable_by_generic_lab_units": false,
      "inferable_by_multilingual_label_map": false,
      "recommended_strategy": "table_geometry_header_inference",
      "confidence_band": "high"
    },
    {
      "safe_file_id": "corpus_file_000423",
      "file_type": "pdf",
      "extension": ".pdf",
      "page_count_bucket": "1",
      "structure_error": null,
      "text_length_bucket": "200_1000",
      "numeric_density_bucket": "high_30_50pct",
      "table_like_line_count_bucket": "zero",
      "short_line_ratio_bucket": "very_high_gt_50pct",
      "unit_pattern_count_bucket": "zero",
      "reference_range_pattern_count_bucket": "zero",
      "repeated_numeric_column_pattern": false,
      "likely_table_present": true,
      "likely_header_missing": true,
      "likely_header_fragmented": false,
      "likely_non_english_labels": false,
      "likely_cyrillic_or_mixed_script_labels": false,
      "likely_units_without_analyte_names": false,
      "likely_analyte_names_without_units": false,
      "inferable_by_neighbor_lines": false,
      "inferable_by_table_geometry": true,
      "inferable_by_generic_lab_units": false,
      "inferable_by_multilingual_label_map": false,
      "recommended_strategy": "table_geometry_header_inference",
      "confidence_band": "high"
    },
    {
      "safe_file_id": "corpus_file_000439",
      "file_type": "pdf",
      "extension": ".pdf",
      "page_count_bucket": "1",
      "structure_error": null,
      "text_length_bucket": "200_1000",
      "numeric_density_bucket": "high_30_50pct",
      "table_like_line_count_bucket": "zero",
      "short_line_ratio_bucket": "very_high_gt_50pct",
      "unit_pattern_count_bucket": "zero",
      "reference_range_pattern_count_bucket": "zero",
      "repeated_numeric_column_pattern": false,
      "likely_table_present": true,
      "likely_header_missing": true,
      "likely_header_fragmented": false,
      "likely_non_english_labels": false,
      "likely_cyrillic_or_mixed_script_labels": false,
      "likely_units_without_analyte_names": false,
      "likely_analyte_names_without_units": false,
      "inferable_by_neighbor_lines": false,
      "inferable_by_table_geometry": true,
      "inferable_by_generic_lab_units": false,
      "inferable_by_multilingual_label_map": false,
      "recommended_strategy": "table_geometry_header_inference",
      "confidence_band": "high"
    },
    {
      "safe_file_id": "corpus_file_000440",
      "file_type": "pdf",
      "extension": ".pdf",
      "page_count_bucket": "1",
      "structure_error": null,
      "text_length_bucket": "200_1000",
      "numeric_density_bucket": "very_high_gt_50pct",
      "table_like_line_count_bucket": "zero",
      "short_line_ratio_bucket": "very_high_gt_50pct",
      "unit_pattern_count_bucket": "zero",
      "reference_range_pattern_count_bucket": "zero",
      "repeated_numeric_column_pattern": false,
      "likely_table_present": true,
      "likely_header_missing": true,
      "likely_header_fragmented": false,
      "likely_non_english_labels": false,
      "likely_cyrillic_or_mixed_script_labels": false,
      "likely_units_without_analyte_names": false,
      "likely_analyte_names_without_units": false,
      "inferable_by_neighbor_lines": false,
      "inferable_by_table_geometry": true,
      "inferable_by_generic_lab_units": false,
      "inferable_by_multilingual_label_map": false,
      "recommended_strategy": "table_geometry_header_inference",
      "confidence_band": "high"
    },
    {
      "safe_file_id": "corpus_file_000449",
      "file_type": "pdf",
      "extension": ".pdf",
      "page_count_bucket": "1",
      "structure_error": null,
      "text_length_bucket": "200_1000",
      "numeric_density_bucket": "high_30_50pct",
      "table_like_line_count_bucket": "zero",
      "short_line_ratio_bucket": "very_high_gt_50pct",
      "unit_pattern_count_bucket": "zero",
      "reference_range_pattern_count_bucket": "zero",
      "repeated_numeric_column_pattern": false,
      "likely_table_present": true,
      "likely_header_missing": true,
      "likely_header_fragmented": false,
      "likely_non_english_labels": false,
      "likely_cyrillic_or_mixed_script_labels": false,
      "likely_units_without_analyte_names": false,
      "likely_analyte_names_without_units": false,
      "inferable_by_neighbor_lines": false,
      "inferable_by_table_geometry": true,
      "inferable_by_generic_lab_units": false,
      "inferable_by_multilingual_label_map": false,
      "recommended_strategy": "table_geometry_header_inference",
      "confidence_band": "high"
    },
    {
      "safe_file_id": "corpus_file_000473",
      "file_type": "pdf",
      "extension": ".pdf",
      "page_count_bucket": "1",
      "structure_error": null,
      "text_length_bucket": "200_1000",
      "numeric_density_bucket": "high_30_50pct",
      "table_like_line_count_bucket": "zero",
      "short_line_ratio_bucket": "very_high_gt_50pct",
      "unit_pattern_count_bucket": "zero",
      "reference_range_pattern_count_bucket": "zero",
      "repeated_numeric_column_pattern": false,
      "likely_table_present": true,
      "likely_header_missing": true,
      "likely_header_fragmented": false,
      "likely_non_english_labels": false,
      "likely_cyrillic_or_mixed_script_labels": false,
      "likely_units_without_analyte_names": false,
      "likely_analyte_names_without_units": false,
      "inferable_by_neighbor_lines": false,
      "inferable_by_table_geometry": true,
      "inferable_by_generic_lab_units": false,
      "inferable_by_multilingual_label_map": false,
      "recommended_strategy": "table_geometry_header_inference",
      "confidence_band": "high"
    },
    {
      "safe_file_id": "corpus_file_000476",
      "file_type": "pdf",
      "extension": ".pdf",
      "page_count_bucket": "1",
      "structure_error": null,
      "text_length_bucket": "200_1000",
      "numeric_density_bucket": "high_30_50pct",
      "table_like_line_count_bucket": "zero",
      "short_line_ratio_bucket": "very_high_gt_50pct",
      "unit_pattern_count_bucket": "zero",
      "reference_range_pattern_count_bucket": "zero",
      "repeated_numeric_column_pattern": false,
      "likely_table_present": true,
      "likely_header_missing": true,
      "likely_header_fragmented": false,
      "likely_non_english_labels": false,
      "likely_cyrillic_or_mixed_script_labels": false,
      "likely_units_without_analyte_names": false,
      "likely_analyte_names_without_units": false,
      "inferable_by_neighbor_lines": false,
      "inferable_by_table_geometry": true,
      "inferable_by_generic_lab_units": false,
      "inferable_by_multilingual_label_map": false,
      "recommended_strategy": "table_geometry_header_inference",
      "confidence_band": "high"
    },
    {
      "safe_file_id": "corpus_file_000499",
      "file_type": "pdf",
      "extension": ".pdf",
      "page_count_bucket": "1",
      "structure_error": null,
      "text_length_bucket": "200_1000",
      "numeric_density_bucket": "high_30_50pct",
      "table_like_line_count_bucket": "zero",
      "short_line_ratio_bucket": "very_high_gt_50pct",
      "unit_pattern_count_bucket": "zero",
      "reference_range_pattern_count_bucket": "zero",
      "repeated_numeric_column_pattern": false,
      "likely_table_present": true,
      "likely_header_missing": true,
      "likely_header_fragmented": false,
      "likely_non_english_labels": false,
      "likely_cyrillic_or_mixed_script_labels": false,
      "likely_units_without_analyte_names": false,
      "likely_analyte_names_without_units": false,
      "inferable_by_neighbor_lines": false,
      "inferable_by_table_geometry": true,
      "inferable_by_generic_lab_units": false,
      "inferable_by_multilingual_label_map": false,
      "recommended_strategy": "table_geometry_header_inference",
      "confidence_band": "high"
    },
    {
      "safe_file_id": "corpus_file_000507",
      "file_type": "pdf",
      "extension": ".pdf",
      "page_count_bucket": "2_3",
      "structure_error": null,
      "text_length_bucket": "1000_5000",
      "numeric_density_bucket": "high_30_50pct",
      "table_like_line_count_bucket": "zero",
      "short_line_ratio_bucket": "very_high_gt_50pct",
      "unit_pattern_count_bucket": "zero",
      "reference_range_pattern_count_bucket": "zero",
      "repeated_numeric_column_pattern": false,
      "likely_table_present": true,
      "likely_header_missing": true,
      "likely_header_fragmented": false,
      "likely_non_english_labels": false,
      "likely_cyrillic_or_mixed_script_labels": false,
      "likely_units_without_analyte_names": false,
      "likely_analyte_names_without_units": false,
      "inferable_by_neighbor_lines": false,
      "inferable_by_table_geometry": true,
      "inferable_by_generic_lab_units": false,
      "inferable_by_multilingual_label_map": false,
      "recommended_strategy": "table_geometry_header_inference",
      "confidence_band": "high"
    },
    {
      "safe_file_id": "corpus_file_000513",
      "file_type": "pdf",
      "extension": ".pdf",
      "page_count_bucket": "2_3",
      "structure_error": null,
      "text_length_bucket": "1000_5000",
      "numeric_density_bucket": "high_30_50pct",
      "table_like_line_count_bucket": "zero",
      "short_line_ratio_bucket": "very_high_gt_50pct",
      "unit_pattern_count_bucket": "zero",
      "reference_range_pattern_count_bucket": "zero",
      "repeated_numeric_column_pattern": false,
      "likely_table_present": true,
      "likely_header_missing": true,
      "likely_header_fragmented": false,
      "likely_non_english_labels": false,
      "likely_cyrillic_or_mixed_script_labels": false,
      "likely_units_without_analyte_names": false,
      "likely_analyte_names_without_units": false,
      "inferable_by_neighbor_lines": false,
      "inferable_by_table_geometry": true,
      "inferable_by_generic_lab_units": false,
      "inferable_by_multilingual_label_map": false,
      "recommended_strategy": "table_geometry_header_inference",
      "confidence_band": "high"
    },
    {
      "safe_file_id": "corpus_file_000515",
      "file_type": "pdf",
      "extension": ".pdf",
      "page_count_bucket": "1",
      "structure_error": null,
      "text_length_bucket": "200_1000",
      "numeric_density_bucket": "high_30_50pct",
      "table_like_line_count_bucket": "zero",
      "short_line_ratio_bucket": "very_high_gt_50pct",
      "unit_pattern_count_bucket": "zero",
      "reference_range_pattern_count_bucket": "zero",
      "repeated_numeric_column_pattern": false,
      "likely_table_present": true,
      "likely_header_missing": true,
      "likely_header_fragmented": false,
      "likely_non_english_labels": false,
      "likely_cyrillic_or_mixed_script_labels": false,
      "likely_units_without_analyte_names": false,
      "likely_analyte_names_without_units": false,
      "inferable_by_neighbor_lines": false,
      "inferable_by_table_geometry": true,
      "inferable_by_generic_lab_units": false,
      "inferable_by_multilingual_label_map": false,
      "recommended_strategy": "table_geometry_header_inference",
      "confidence_band": "high"
    }
  ],
  "privacy_safety": {
    "uses_safe_ids_only": true,
    "raw_filenames_present_in_output": false,
    "raw_paths_present_in_output": false,
    "extracted_text_present_in_output": false,
    "ocr_text_present_in_output": false,
    "table_rows_or_labels_in_output": false,
    "phi_present_in_output": false,
    "external_api_used": false
  },
  "conclusion": "header_label_inference_diagnosed"
}